clickhouse_plantuml/__init__.py
clickhouse_plantuml/__main__.py
clickhouse_plantuml/client.py
clickhouse_plantuml/column.py
clickhouse_plantuml/plantuml.py
clickhouse_plantuml/table.py
clickhouse_plantuml/tables.py
clickhouse_plantuml/version.py
clickhouse_plantuml-0.2.2.data/data/LICENSE
clickhouse_plantuml-0.2.2.data/data/example.png
tests/__init__.py
tests/test_plantuml.py
clickhouse_plantuml-0.2.2.dist-info/LICENSE
clickhouse_plantuml-0.2.2.dist-info/METADATA
clickhouse_plantuml-0.2.2.dist-info/WHEEL
clickhouse_plantuml-0.2.2.dist-info/entry_points.txt
clickhouse_plantuml-0.2.2.dist-info/top_level.txt
clickhouse_plantuml-0.2.2.dist-info/RECORD
