Metadata-Version: 2.1
Name: clickhouse-plantuml
Version: 0.2.2
Summary: Generates PlantUML diagrams for clickhouse databases
Home-page: http://github.com/Felixoid/clickhouse-plantuml
Author: Mikhail f. Shiryaev
Author-email: mr.felixoid@gmail.com
License: License :: OSI Approved :: Apache Software License
Platform: UNKNOWN
Classifier: Development Status :: 4 - Beta
Classifier: Intended Audience :: Developers
Classifier: Intended Audience :: Information Technology
Classifier: Intended Audience :: Science/Research
Classifier: Intended Audience :: System Administrators
Classifier: Programming Language :: Python :: 3.5
Classifier: Programming Language :: Python :: 3.6
Classifier: Programming Language :: Python :: 3.7
Classifier: Programming Language :: Python :: 3.8
Classifier: Topic :: Database
Classifier: Topic :: Scientific/Engineering :: Information Analysis
Classifier: Topic :: Scientific/Engineering :: Visualization
Classifier: Topic :: Software Development :: Documentation
Classifier: Topic :: Software Development :: Libraries
Requires-Python: ~=3.5
Requires-Dist: clickhouse-driver
Provides-Extra: black
Requires-Dist: black ; extra == 'black'
Requires-Dist: pytest-black ; extra == 'black'
Provides-Extra: tests
Requires-Dist: pytest ; extra == 'tests'
Requires-Dist: pytest-docker ; extra == 'tests'
Requires-Dist: flake8 ; extra == 'tests'
